{
  "totalProducts": 158,
  "updatedCount": 158,
  "applied": [
    {
      "id": "6a0d8905d38ea5fe36d78601",
      "before": {
        "slug": "casio-g-shock-original-o6aaxg",
        "images": [],
        "isActive": true
      },
      "after": {
        "slug": "casio-g-shock-original-o6aaxg",
        "sku": "SKU-d78601",
        "images": [],
        "variants": [
          {
            "sku": "SKU-d78601",
            "price": 1500000,
            "title": "Casio G-Shock Original",
            "isDefault": true
          }
        ],
        "isActive": true
      }
    },
    {
      "id": "6a0d8905d38ea5fe36d78602",
      "before": {
        "slug": "casio-g-shock-original-3gy3",
        "images": [],
        "isActive": true
      },
      "after": {
        "slug": "casio-g-shock-original-3gy3",
        "sku": "SKU-d78602",
        "images": [],
        "variants": [
          {
            "sku": "SKU-d78602",
            "price": 1500000,
            "title": "Casio G-Shock Original",
            "isDefault": true
          }
        ],
        "isActive": true
      }
    },
    {
      "id": "6a0d8905d38ea5fe36d78603",
      "before": {
        "slug": "casio-g-shock-original-cnl4l",
        "images": [],
        "isActive": true
      },
      "after": {
        "slug": "casio-g-shock-original-cnl4l",
        "sku": "SKU-d78603",
        "images": [],
        "variants": [
          {
            "sku": "SKU-d78603",
            "price": 1500000,
            "title": "Casio G-Shock Original",
            "isDefault": true
          }
        ],
        "isActive": true
      }
    },
    {
      "id": "6a0d8905d38ea5fe36d78604",
      "before": {
        "slug": "casio-g-shock-casioak-88nza",
        "images": [],
        "isActive": true
      },
      "after": {
        "slug": "casio-g-shock-casioak-88nza",
        "sku": "SKU-d78604",
        "images": [],
        "variants": [
          {
            "sku": "SKU-d78604",
            "price": 2940000,
            "title": "Casio G-Shock CasiOak",
            "isDefault": true
          }
        ],
        "isActive": true
      }
    },
    {
      "id": "6a0d8905d38ea5fe36d78605",
      "before": {
        "slug": "casio-g-shock-casioak-70320k",
        "images": [],
        "isActive": true
      },
      "after": {
        "slug": "casio-g-shock-casioak-70320k",
        "sku": "SKU-d78605",
        "images": [],
        "variants": [
          {
            "sku": "SKU-d78605",
            "price": 2940000,
            "title": "Casio G-Shock CasiOak",
            "isDefault": true
          }
        ],
        "isActive": true
      }
    },
    {
      "id": "6a0d8905d38ea5fe36d78606",
      "before": {
        "slug": "casio-g-shock-casioak-4cp52",
        "images": [],
        "isActive": true
      },
      "after": {
        "slug": "casio-g-shock-casioak-4cp52",
        "sku": "SKU-d78606",
        "images": [],
        "variants": [
          {
            "sku": "SKU-d78606",
            "price": 2940000,
            "title": "Casio G-Shock CasiOak",
            "isDefault": true
          }
        ],
        "isActive": true
      }
    },
    {
      "id": "6a0d8905d38ea5fe36d78607",
      "before": {
        "slug": "casio-g-shock-casioak-qvhxp",
        "images": [],
        "isActive": true
      },
      "after": {
        "slug": "casio-g-shock-casioak-qvhxp",
        "sku": "SKU-d78607",
        "images": [],
        "variants": [
          {
            "sku": "SKU-d78607",
            "price": 2940000,
            "title": "Casio G-Shock CasiOak",
            "isDefault": true
          }
        ],
        "isActive": true
      }
    },
    {
      "id": "6a0d8905d38ea5fe36d78608",
      "before": {
        "slug": "casio-classic-f-91w-rkzo5q",
        "images": [],
        "isActive": true
      },
      "after": {
        "slug": "casio-classic-f-91w-rkzo5q",
        "sku": "SKU-d78608",
        "images": [],
        "variants": [
          {
            "sku": "SKU-d78608",
            "price": 400000,
            "title": "Casio Classic F-91W",
            "isDefault": true
          }
        ],
        "isActive": true
      }
    },
    {
      "id": "6a0d8905d38ea5fe36d78609",
      "before": {
        "slug": "casio-classic-f-91w-o600qx",
        "images": [],
        "isActive": true
      },
      "after": {
        "slug": "casio-classic-f-91w-o600qx",
        "sku": "SKU-d78609",
        "images": [],
        "variants": [
          {
            "sku": "SKU-d78609",
            "price": 400000,
            "title": "Casio Classic F-91W",
            "isDefault": true
          }
        ],
        "isActive": true
      }
    },
    {
      "id": "6a0d8905d38ea5fe36d7860a",
      "before": {
        "slug": "casio-classic-f-91w-xax53",
        "images": [],
        "isActive": true
      },
      "after": {
        "slug": "casio-classic-f-91w-xax53",
        "sku": "SKU-d7860a",
        "images": [],
        "variants": [
          {
            "sku": "SKU-d7860a",
            "price": 400000,
            "title": "Casio Classic F-91W",
            "isDefault": true
          }
        ],
        "isActive": true
      }
    },
    {
      "id": "6a0d8905d38ea5fe36d7860b",
      "before": {
        "slug": "casio-classic-f-91w-rwu9bw",
        "images": [],
        "isActive": true
      },
      "after": {
        "slug": "casio-classic-f-91w-rwu9bw",
        "sku": "SKU-d7860b",
        "images": [],
        "variants": [
          {
            "sku": "SKU-d7860b",
            "price": 400000,
            "title": "Casio Classic F-91W",
            "isDefault": true
          }
        ],
        "isActive": true
      }
    },
    {
      "id": "6a0d8905d38ea5fe36d7860c",
      "before": {
        "slug": "casio-classic-f-91w-bi7b38",
        "images": [],
        "isActive": true
      },
      "after": {
        "slug": "casio-classic-f-91w-bi7b38",
        "sku": "SKU-d7860c",
        "images": [],
        "variants": [
          {
            "sku": "SKU-d7860c",
            "price": 400000,
            "title": "Casio Classic F-91W",
            "isDefault": true
          }
        ],
        "isActive": true
      }
    },
    {
      "id": "6a0d8905d38ea5fe36d7860d",
      "before": {
        "slug": "casio-classic-f-91w-c0aewt",
        "images": [],
        "isActive": true
      },
      "after": {
        "slug": "casio-classic-f-91w-c0aewt",
        "sku": "SKU-d7860d",
        "images": [],
        "variants": [
          {
            "sku": "SKU-d7860d",
            "price": 400000,
            "title": "Casio Classic F-91W",
            "isDefault": true
          }
        ],
        "isActive": true
      }
    },
    {
      "id": "6a0d8905d38ea5fe36d7860e",
      "before": {
        "slug": "casio-edifice-chronograph-673sv",
        "images": [],
        "isActive": true
      },
      "after": {
        "slug": "casio-edifice-chronograph-673sv",
        "sku": "SKU-d7860e",
        "images": [],
        "variants": [
          {
            "sku": "SKU-d7860e",
            "price": 3500000,
            "title": "Casio Edifice Chronograph",
            "isDefault": true
          }
        ],
        "isActive": true
      }
    },
    {
      "id": "6a0d8905d38ea5fe36d7860f",
      "before": {
        "slug": "casio-edifice-chronograph-k59aal",
        "images": [],
        "isActive": true
      },
      "after": {
        "slug": "casio-edifice-chronograph-k59aal",
        "sku": "SKU-d7860f",
        "images": [],
        "variants": [
          {
            "sku": "SKU-d7860f",
            "price": 3500000,
            "title": "Casio Edifice Chronograph",
            "isDefault": true
          }
        ],
        "isActive": true
      }
    },
    {
      "id": "6a0d8905d38ea5fe36d78610",
      "before": {
        "slug": "casio-edifice-chronograph-4uwrpb",
        "images": [],
        "isActive": true
      },
      "after": {
        "slug": "casio-edifice-chronograph-4uwrpb",
        "sku": "SKU-d78610",
        "images": [],
        "variants": [
          {
            "sku": "SKU-d78610",
            "price": 3500000,
            "title": "Casio Edifice Chronograph",
            "isDefault": true
          }
        ],
        "isActive": true
      }
    },
    {
      "id": "6a0d8905d38ea5fe36d78611",
      "before": {
        "slug": "seiko-5-sports-skx-style-23xtzo",
        "images": [],
        "isActive": true
      },
      "after": {
        "slug": "seiko-5-sports-skx-style-23xtzo",
        "sku": "SKU-d78611",
        "images": [],
        "variants": [
          {
            "sku": "SKU-d78611",
            "price": 6500000,
            "title": "Seiko 5 Sports (SKX Style)",
            "isDefault": true
          }
        ],
        "isActive": true
      }
    },
    {
      "id": "6a0d8905d38ea5fe36d78612",
      "before": {
        "slug": "seiko-5-sports-skx-style-m93f",
        "images": [],
        "isActive": true
      },
      "after": {
        "slug": "seiko-5-sports-skx-style-m93f",
        "sku": "SKU-d78612",
        "images": [],
        "variants": [
          {
            "sku": "SKU-d78612",
            "price": 6500000,
            "title": "Seiko 5 Sports (SKX Style)",
            "isDefault": true
          }
        ],
        "isActive": true
      }
    },
    {
      "id": "6a0d8905d38ea5fe36d78613",
      "before": {
        "slug": "seiko-5-sports-skx-style-y795l",
        "images": [],
        "isActive": true
      },
      "after": {
        "slug": "seiko-5-sports-skx-style-y795l",
        "sku": "SKU-d78613",
        "images": [],
        "variants": [
          {
            "sku": "SKU-d78613",
            "price": 6500000,
            "title": "Seiko 5 Sports (SKX Style)",
            "isDefault": true
          }
        ],
        "isActive": true
      }
    },
    {
      "id": "6a0d8905d38ea5fe36d78614",
      "before": {
        "slug": "seiko-5-sports-skx-style-45aes5",
        "images": [],
        "isActive": true
      },
      "after": {
        "slug": "seiko-5-sports-skx-style-45aes5",
        "sku": "SKU-d78614",
        "images": [],
        "variants": [
          {
            "sku": "SKU-d78614",
            "price": 6500000,
            "title": "Seiko 5 Sports (SKX Style)",
            "isDefault": true
          }
        ],
        "isActive": true
      }
    },
    {
      "id": "6a0d8905d38ea5fe36d78615",
      "before": {
        "slug": "seiko-5-sports-skx-style-znc6f",
        "images": [],
        "isActive": true
      },
      "after": {
        "slug": "seiko-5-sports-skx-style-znc6f",
        "sku": "SKU-d78615",
        "images": [],
        "variants": [
          {
            "sku": "SKU-d78615",
            "price": 6500000,
            "title": "Seiko 5 Sports (SKX Style)",
            "isDefault": true
          }
        ],
        "isActive": true
      }
    },
    {
      "id": "6a0d8905d38ea5fe36d78616",
      "before": {
        "slug": "seiko-prospex-diver-turtle-411x71",
        "images": [],
        "isActive": true
      },
      "after": {
        "slug": "seiko-prospex-diver-turtle-411x71",
        "sku": "SKU-d78616",
        "images": [],
        "variants": [
          {
            "sku": "SKU-d78616",
            "price": 11030000,
            "title": "Seiko Prospex Diver (Turtle)",
            "isDefault": true
          }
        ],
        "isActive": true
      }
    },
    {
      "id": "6a0d8905d38ea5fe36d78617",
      "before": {
        "slug": "seiko-prospex-diver-turtle-cd3xd",
        "images": [],
        "isActive": true
      },
      "after": {
        "slug": "seiko-prospex-diver-turtle-cd3xd",
        "sku": "SKU-d78617",
        "images": [],
        "variants": [
          {
            "sku": "SKU-d78617",
            "price": 11030000,
            "title": "Seiko Prospex Diver (Turtle)",
            "isDefault": true
          }
        ],
        "isActive": true
      }
    },
    {
      "id": "6a0d8905d38ea5fe36d78618",
      "before": {
        "slug": "seiko-prospex-diver-turtle-rqwqj",
        "images": [],
        "isActive": true
      },
      "after": {
        "slug": "seiko-prospex-diver-turtle-rqwqj",
        "sku": "SKU-d78618",
        "images": [],
        "variants": [
          {
            "sku": "SKU-d78618",
            "price": 11030000,
            "title": "Seiko Prospex Diver (Turtle)",
            "isDefault": true
          }
        ],
        "isActive": true
      }
    },
    {
      "id": "6a0d8905d38ea5fe36d78619",
      "before": {
        "slug": "seiko-presage-cocktail-time-7sg6w",
        "images": [],
        "isActive": true
      },
      "after": {
        "slug": "seiko-presage-cocktail-time-7sg6w",
        "sku": "SKU-d78619",
        "images": [],
        "variants": [
          {
            "sku": "SKU-d78619",
            "price": 11000000,
            "title": "Seiko Presage Cocktail Time",
            "isDefault": true
          }
        ],
        "isActive": true
      }
    },
    {
      "id": "6a0d8905d38ea5fe36d7861a",
      "before": {
        "slug": "seiko-presage-cocktail-time-0ln21d",
        "images": [],
        "isActive": true
      },
      "after": {
        "slug": "seiko-presage-cocktail-time-0ln21d",
        "sku": "SKU-d7861a",
        "images": [],
        "variants": [
          {
            "sku": "SKU-d7861a",
            "price": 11000000,
            "title": "Seiko Presage Cocktail Time",
            "isDefault": true
          }
        ],
        "isActive": true
      }
    },
    {
      "id": "6a0d8905d38ea5fe36d7861b",
      "before": {
        "slug": "seiko-presage-cocktail-time-u3urwb",
        "images": [],
        "isActive": true
      },
      "after": {
        "slug": "seiko-presage-cocktail-time-u3urwb",
        "sku": "SKU-d7861b",
        "images": [],
        "variants": [
          {
            "sku": "SKU-d7861b",
            "price": 11000000,
            "title": "Seiko Presage Cocktail Time",
            "isDefault": true
          }
        ],
        "isActive": true
      }
    },
    {
      "id": "6a0d8905d38ea5fe36d7861c",
      "before": {
        "slug": "seiko-presage-cocktail-time-9a20tk",
        "images": [],
        "isActive": true
      },
      "after": {
        "slug": "seiko-presage-cocktail-time-9a20tk",
        "sku": "SKU-d7861c",
        "images": [],
        "variants": [
          {
            "sku": "SKU-d7861c",
            "price": 11000000,
            "title": "Seiko Presage Cocktail Time",
            "isDefault": true
          }
        ],
        "isActive": true
      }
    },
    {
      "id": "6a0d8905d38ea5fe36d7861d",
      "before": {
        "slug": "seiko-alpinist-43u82",
        "images": [],
        "isActive": true
      },
      "after": {
        "slug": "seiko-alpinist-43u82",
        "sku": "SKU-d7861d",
        "images": [],
        "variants": [
          {
            "sku": "SKU-d7861d",
            "price": 18000000,
            "title": "Seiko Alpinist",
            "isDefault": true
          }
        ],
        "isActive": true
      }
    },
    {
      "id": "6a0d8905d38ea5fe36d7861e",
      "before": {
        "slug": "seiko-alpinist-itsd95",
        "images": [],
        "isActive": true
      },
      "after": {
        "slug": "seiko-alpinist-itsd95",
        "sku": "SKU-d7861e",
        "images": [],
        "variants": [
          {
            "sku": "SKU-d7861e",
            "price": 18000000,
            "title": "Seiko Alpinist",
            "isDefault": true
          }
        ],
        "isActive": true
      }
    },
    {
      "id": "6a0d8905d38ea5fe36d7861f",
      "before": {
        "slug": "seiko-alpinist-iuyn2",
        "images": [],
        "isActive": true
      },
      "after": {
        "slug": "seiko-alpinist-iuyn2",
        "sku": "SKU-d7861f",
        "images": [],
        "variants": [
          {
            "sku": "SKU-d7861f",
            "price": 18000000,
            "title": "Seiko Alpinist",
            "isDefault": true
          }
        ],
        "isActive": true
      }
    },
    {
      "id": "6a0d8905d38ea5fe36d785d1",
      "before": {
        "slug": "rolex-submariner-date-14c2qi",
        "images": [],
        "isActive": true
      },
      "after": {
        "slug": "rolex-submariner-date-14c2qi",
        "sku": "SKU-d785d1",
        "images": [],
        "variants": [
          {
            "sku": "SKU-d785d1",
            "price": 280000000,
            "title": "Rolex Submariner Date",
            "isDefault": true
          }
        ],
        "isActive": true
      }
    },
    {
      "id": "6a0d8905d38ea5fe36d785d2",
      "before": {
        "slug": "rolex-submariner-date-w36zuq",
        "images": [],
        "isActive": true
      },
      "after": {
        "slug": "rolex-submariner-date-w36zuq",
        "sku": "SKU-d785d2",
        "images": [],
        "variants": [
          {
            "sku": "SKU-d785d2",
            "price": 280000000,
            "title": "Rolex Submariner Date",
            "isDefault": true
          }
        ],
        "isActive": true
      }
    },
    {
      "id": "6a0d8905d38ea5fe36d785d3",
      "before": {
        "slug": "rolex-submariner-no-date-dd9l4",
        "sku": "",
        "images": [],
        "isActive": true
      },
      "after": {
        "slug": "rolex-submariner-no-date-dd9l4",
        "sku": "SKU-d785d3",
        "images": [],
        "variants": [
          {
            "sku": "SKU-d785d3",
            "price": 240000000,
            "title": "Rolex Submariner No-Date",
            "isDefault": true
          }
        ],
        "isActive": true
      }
    },
    {
      "id": "6a0d8905d38ea5fe36d785d4",
      "before": {
        "slug": "rolex-daytona-ty64lc",
        "images": [],
        "isActive": true
      },
      "after": {
        "slug": "rolex-daytona-ty64lc",
        "sku": "SKU-d785d4",
        "images": [],
        "variants": [
          {
            "sku": "SKU-d785d4",
            "price": 650000000,
            "title": "Rolex Daytona",
            "isDefault": true
          }
        ],
        "isActive": true
      }
    },
    {
      "id": "6a0d8905d38ea5fe36d785d5",
      "before": {
        "slug": "rolex-daytona-c6jzd",
        "images": [],
        "isActive": true
      },
      "after": {
        "slug": "rolex-daytona-c6jzd",
        "sku": "SKU-d785d5",
        "images": [],
        "variants": [
          {
            "sku": "SKU-d785d5",
            "price": 650000000,
            "title": "Rolex Daytona",
            "isDefault": true
          }
        ],
        "isActive": true
      }
    },
    {
      "id": "6a0d8905d38ea5fe36d785d6",
      "before": {
        "slug": "rolex-gmt-master-ii-mu8rco",
        "images": [],
        "isActive": true
      },
      "after": {
        "slug": "rolex-gmt-master-ii-mu8rco",
        "sku": "SKU-d785d6",
        "images": [],
        "variants": [
          {
            "sku": "SKU-d785d6",
            "price": 350000000,
            "title": "Rolex GMT-Master II",
            "isDefault": true
          }
        ],
        "isActive": true
      }
    },
    {
      "id": "6a0d8905d38ea5fe36d785d7",
      "before": {
        "slug": "rolex-gmt-master-ii-qhsiw8",
        "images": [],
        "isActive": true
      },
      "after": {
        "slug": "rolex-gmt-master-ii-qhsiw8",
        "sku": "SKU-d785d7",
        "images": [],
        "variants": [
          {
            "sku": "SKU-d785d7",
            "price": 350000000,
            "title": "Rolex GMT-Master II",
            "isDefault": true
          }
        ],
        "isActive": true
      }
    },
    {
      "id": "6a0d8905d38ea5fe36d785d8",
      "before": {
        "slug": "rolex-gmt-master-ii-x0eeo6",
        "images": [],
        "isActive": true
      },
      "after": {
        "slug": "rolex-gmt-master-ii-x0eeo6",
        "sku": "SKU-d785d8",
        "images": [],
        "variants": [
          {
            "sku": "SKU-d785d8",
            "price": 350000000,
            "title": "Rolex GMT-Master II",
            "isDefault": true
          }
        ],
        "isActive": true
      }
    },
    {
      "id": "6a0d8905d38ea5fe36d785d9",
      "before": {
        "slug": "rolex-datejust-36-yzsey8",
        "images": [],
        "isActive": true
      },
      "after": {
        "slug": "rolex-datejust-36-yzsey8",
        "sku": "SKU-d785d9",
        "images": [],
        "variants": [
          {
            "sku": "SKU-d785d9",
            "price": 220000000,
            "title": "Rolex Datejust 36",
            "isDefault": true
          }
        ],
        "isActive": true
      }
    },
    {
      "id": "6a0d8905d38ea5fe36d785da",
      "before": {
        "slug": "rolex-datejust-36-0fis2f",
        "images": [],
        "isActive": true
      },
      "after": {
        "slug": "rolex-datejust-36-0fis2f",
        "sku": "SKU-d785da",
        "images": [],
        "variants": [
          {
            "sku": "SKU-d785da",
            "price": 220000000,
            "title": "Rolex Datejust 36",
            "isDefault": true
          }
        ],
        "isActive": true
      }
    },
    {
      "id": "6a0d8905d38ea5fe36d785db",
      "before": {
        "slug": "rolex-datejust-36-ocqdc4",
        "images": [],
        "isActive": true
      },
      "after": {
        "slug": "rolex-datejust-36-ocqdc4",
        "sku": "SKU-d785db",
        "images": [],
        "variants": [
          {
            "sku": "SKU-d785db",
            "price": 220000000,
            "title": "Rolex Datejust 36",
            "isDefault": true
          }
        ],
        "isActive": true
      }
    },
    {
      "id": "6a0d8905d38ea5fe36d785dc",
      "before": {
        "slug": "rolex-datejust-36-vbnv7s",
        "images": [],
        "isActive": true
      },
      "after": {
        "slug": "rolex-datejust-36-vbnv7s",
        "sku": "SKU-d785dc",
        "images": [],
        "variants": [
          {
            "sku": "SKU-d785dc",
            "price": 220000000,
            "title": "Rolex Datejust 36",
            "isDefault": true
          }
        ],
        "isActive": true
      }
    },
    {
      "id": "6a0d8905d38ea5fe36d785dd",
      "before": {
        "slug": "rolex-datejust-36-4qgx8g",
        "images": [],
        "isActive": true
      },
      "after": {
        "slug": "rolex-datejust-36-4qgx8g",
        "sku": "SKU-d785dd",
        "images": [],
        "variants": [
          {
            "sku": "SKU-d785dd",
            "price": 220000000,
            "title": "Rolex Datejust 36",
            "isDefault": true
          }
        ],
        "isActive": true
      }
    },
    {
      "id": "6a0d8905d38ea5fe36d785de",
      "before": {
        "slug": "rolex-datejust-36-gnmak",
        "images": [],
        "isActive": true
      },
      "after": {
        "slug": "rolex-datejust-36-gnmak",
        "sku": "SKU-d785de",
        "images": [],
        "variants": [
          {
            "sku": "SKU-d785de",
            "price": 220000000,
            "title": "Rolex Datejust 36",
            "isDefault": true
          }
        ],
        "isActive": true
      }
    },
    {
      "id": "6a0d8905d38ea5fe36d785df",
      "before": {
        "slug": "rolex-oyster-perpetual-iiyvlr",
        "images": [],
        "isActive": true
      },
      "after": {
        "slug": "rolex-oyster-perpetual-iiyvlr",
        "sku": "SKU-d785df",
        "images": [],
        "variants": [
          {
            "sku": "SKU-d785df",
            "price": 180000000,
            "title": "Rolex Oyster Perpetual",
            "isDefault": true
          }
        ],
        "isActive": true
      }
    },
    {
      "id": "6a0d8905d38ea5fe36d785e0",
      "before": {
        "slug": "rolex-oyster-perpetual-9do1iw",
        "images": [],
        "isActive": true
      },
      "after": {
        "slug": "rolex-oyster-perpetual-9do1iw",
        "sku": "SKU-d785e0",
        "images": [],
        "variants": [
          {
            "sku": "SKU-d785e0",
            "price": 180000000,
            "title": "Rolex Oyster Perpetual",
            "isDefault": true
          }
        ],
        "isActive": true
      }
    },
    {
      "id": "6a0d8905d38ea5fe36d785e1",
      "before": {
        "slug": "rolex-oyster-perpetual-8xlhc6",
        "images": [],
        "isActive": true
      },
      "after": {
        "slug": "rolex-oyster-perpetual-8xlhc6",
        "sku": "SKU-d785e1",
        "images": [],
        "variants": [
          {
            "sku": "SKU-d785e1",
            "price": 180000000,
            "title": "Rolex Oyster Perpetual",
            "isDefault": true
          }
        ],
        "isActive": true
      }
    },
    {
      "id": "6a0d8905d38ea5fe36d785e2",
      "before": {
        "slug": "rolex-oyster-perpetual-esimch",
        "images": [],
        "isActive": true
      },
      "after": {
        "slug": "rolex-oyster-perpetual-esimch",
        "sku": "SKU-d785e2",
        "images": [],
        "variants": [
          {
            "sku": "SKU-d785e2",
            "price": 180000000,
            "title": "Rolex Oyster Perpetual",
            "isDefault": true
          }
        ],
        "isActive": true
      }
    },
    {
      "id": "6a0d8905d38ea5fe36d785e3",
      "before": {
        "slug": "rolex-oyster-perpetual-2wwdgg",
        "images": [],
        "isActive": true
      },
      "after": {
        "slug": "rolex-oyster-perpetual-2wwdgg",
        "sku": "SKU-d785e3",
        "images": [],
        "variants": [
          {
            "sku": "SKU-d785e3",
            "price": 180000000,
            "title": "Rolex Oyster Perpetual",
            "isDefault": true
          }
        ],
        "isActive": true
      }
    },
    {
      "id": "6a0d8905d38ea5fe36d785e4",
      "before": {
        "slug": "rolex-oyster-perpetual-tb40qn",
        "images": [],
        "isActive": true
      },
      "after": {
        "slug": "rolex-oyster-perpetual-tb40qn",
        "sku": "SKU-d785e4",
        "images": [],
        "variants": [
          {
            "sku": "SKU-d785e4",
            "price": 180000000,
            "title": "Rolex Oyster Perpetual",
            "isDefault": true
          }
        ],
        "isActive": true
      }
    },
    {
      "id": "6a0d8905d38ea5fe36d785e5",
      "before": {
        "slug": "rolex-oyster-perpetual-ulb0g",
        "images": [],
        "isActive": true
      },
      "after": {
        "slug": "rolex-oyster-perpetual-ulb0g",
        "sku": "SKU-d785e5",
        "images": [],
        "variants": [
          {
            "sku": "SKU-d785e5",
            "price": 180000000,
            "title": "Rolex Oyster Perpetual",
            "isDefault": true
          }
        ],
        "isActive": true
      }
    },
    {
      "id": "6a0d8905d38ea5fe36d785e6",
      "before": {
        "slug": "rolex-oyster-perpetual-zuiutg",
        "images": [],
        "isActive": true
      },
      "after": {
        "slug": "rolex-oyster-perpetual-zuiutg",
        "sku": "SKU-d785e6",
        "images": [],
        "variants": [
          {
            "sku": "SKU-d785e6",
            "price": 180000000,
            "title": "Rolex Oyster Perpetual",
            "isDefault": true
          }
        ],
        "isActive": true
      }
    },
    {
      "id": "6a0d8905d38ea5fe36d785e7",
      "before": {
        "slug": "rolex-oyster-perpetual-8p8sw",
        "images": [],
        "isActive": true
      },
      "after": {
        "slug": "rolex-oyster-perpetual-8p8sw",
        "sku": "SKU-d785e7",
        "images": [],
        "variants": [
          {
            "sku": "SKU-d785e7",
            "price": 180000000,
            "title": "Rolex Oyster Perpetual",
            "isDefault": true
          }
        ],
        "isActive": true
      }
    },
    {
      "id": "6a0d8905d38ea5fe36d785e8",
      "before": {
        "slug": "rolex-oyster-perpetual-6qu0rb",
        "images": [],
        "isActive": true
      },
      "after": {
        "slug": "rolex-oyster-perpetual-6qu0rb",
        "sku": "SKU-d785e8",
        "images": [],
        "variants": [
          {
            "sku": "SKU-d785e8",
            "price": 180000000,
            "title": "Rolex Oyster Perpetual",
            "isDefault": true
          }
        ],
        "isActive": true
      }
    },
    {
      "id": "6a0d8905d38ea5fe36d785e9",
      "before": {
        "slug": "rolex-oyster-perpetual-z4s7p",
        "images": [],
        "isActive": true
      },
      "after": {
        "slug": "rolex-oyster-perpetual-z4s7p",
        "sku": "SKU-d785e9",
        "images": [],
        "variants": [
          {
            "sku": "SKU-d785e9",
            "price": 180000000,
            "title": "Rolex Oyster Perpetual",
            "isDefault": true
          }
        ],
        "isActive": true
      }
    },
    {
      "id": "6a0d8905d38ea5fe36d785ea",
      "before": {
        "slug": "rolex-oyster-perpetual-vkw8wd",
        "images": [],
        "isActive": true
      },
      "after": {
        "slug": "rolex-oyster-perpetual-vkw8wd",
        "sku": "SKU-d785ea",
        "images": [],
        "variants": [
          {
            "sku": "SKU-d785ea",
            "price": 180000000,
            "title": "Rolex Oyster Perpetual",
            "isDefault": true
          }
        ],
        "isActive": true
      }
    },
    {
      "id": "6a0d8905d38ea5fe36d78633",
      "before": {
        "slug": "audemars-piguet-royal-oak-selfwinding-xekxex",
        "images": [],
        "isActive": true
      },
      "after": {
        "slug": "audemars-piguet-royal-oak-selfwinding-xekxex",
        "sku": "SKU-d78633",
        "images": [],
        "variants": [
          {
            "sku": "SKU-d78633",
            "price": 1200000000,
            "title": "Audemars Piguet Royal Oak Selfwinding",
            "isDefault": true
          }
        ],
        "isActive": true
      }
    },
    {
      "id": "6a0d8905d38ea5fe36d78634",
      "before": {
        "slug": "audemars-piguet-royal-oak-selfwinding-zxq84f",
        "images": [],
        "isActive": true
      },
      "after": {
        "slug": "audemars-piguet-royal-oak-selfwinding-zxq84f",
        "sku": "SKU-d78634",
        "images": [],
        "variants": [
          {
            "sku": "SKU-d78634",
            "price": 1200000000,
            "title": "Audemars Piguet Royal Oak Selfwinding",
            "isDefault": true
          }
        ],
        "isActive": true
      }
    },
    {
      "id": "6a0d8905d38ea5fe36d78635",
      "before": {
        "slug": "audemars-piguet-royal-oak-selfwinding-m2l2ar",
        "images": [],
        "isActive": true
      },
      "after": {
        "slug": "audemars-piguet-royal-oak-selfwinding-m2l2ar",
        "sku": "SKU-d78635",
        "images": [],
        "variants": [
          {
            "sku": "SKU-d78635",
            "price": 1200000000,
            "title": "Audemars Piguet Royal Oak Selfwinding",
            "isDefault": true
          }
        ],
        "isActive": true
      }
    },
    {
      "id": "6a0d8905d38ea5fe36d78636",
      "before": {
        "slug": "audemars-piguet-royal-oak-selfwinding-nrs7qs",
        "images": [],
        "isActive": true
      },
      "after": {
        "slug": "audemars-piguet-royal-oak-selfwinding-nrs7qs",
        "sku": "SKU-d78636",
        "images": [],
        "variants": [
          {
            "sku": "SKU-d78636",
            "price": 1200000000,
            "title": "Audemars Piguet Royal Oak Selfwinding",
            "isDefault": true
          }
        ],
        "isActive": true
      }
    },
    {
      "id": "6a0d8905d38ea5fe36d78637",
      "before": {
        "slug": "audemars-piguet-royal-oak-offshore-diver-pfhi4a",
        "images": [],
        "isActive": true
      },
      "after": {
        "slug": "audemars-piguet-royal-oak-offshore-diver-pfhi4a",
        "sku": "SKU-d78637",
        "images": [],
        "variants": [
          {
            "sku": "SKU-d78637",
            "price": 650000000,
            "title": "Audemars Piguet Royal Oak Offshore Diver",
            "isDefault": true
          }
        ],
        "isActive": true
      }
    },
    {
      "id": "6a0d8905d38ea5fe36d78638",
      "before": {
        "slug": "audemars-piguet-royal-oak-offshore-diver-tby1j",
        "images": [],
        "isActive": true
      },
      "after": {
        "slug": "audemars-piguet-royal-oak-offshore-diver-tby1j",
        "sku": "SKU-d78638",
        "images": [],
        "variants": [
          {
            "sku": "SKU-d78638",
            "price": 650000000,
            "title": "Audemars Piguet Royal Oak Offshore Diver",
            "isDefault": true
          }
        ],
        "isActive": true
      }
    },
    {
      "id": "6a0d8905d38ea5fe36d78639",
      "before": {
        "slug": "audemars-piguet-royal-oak-offshore-diver-2pa9sv",
        "images": [],
        "isActive": true
      },
      "after": {
        "slug": "audemars-piguet-royal-oak-offshore-diver-2pa9sv",
        "sku": "SKU-d78639",
        "images": [],
        "variants": [
          {
            "sku": "SKU-d78639",
            "price": 650000000,
            "title": "Audemars Piguet Royal Oak Offshore Diver",
            "isDefault": true
          }
        ],
        "isActive": true
      }
    },
    {
      "id": "6a0d8905d38ea5fe36d7863a",
      "before": {
        "slug": "audemars-piguet-royal-oak-jumbo-extra-thin-uufqze",
        "images": [],
        "isActive": true
      },
      "after": {
        "slug": "audemars-piguet-royal-oak-jumbo-extra-thin-uufqze",
        "sku": "SKU-d7863a",
        "images": [],
        "variants": [
          {
            "sku": "SKU-d7863a",
            "price": 1800000000,
            "title": "Audemars Piguet Royal Oak Jumbo Extra-Thin",
            "isDefault": true
          }
        ],
        "isActive": true
      }
    },
    {
      "id": "6a0d8905d38ea5fe36d78620",
      "before": {
        "slug": "patek-philippe-nautilus-ddt0lhg",
        "images": [],
        "isActive": true
      },
      "after": {
        "slug": "patek-philippe-nautilus-ddt0lhg",
        "sku": "SKU-d78620",
        "images": [],
        "variants": [
          {
            "sku": "SKU-d78620",
            "price": 1500000000,
            "title": "Patek Philippe Nautilus",
            "isDefault": true
          }
        ],
        "isActive": true
      }
    },
    {
      "id": "6a0d8905d38ea5fe36d78621",
      "before": {
        "slug": "patek-philippe-nautilus-aci1n",
        "images": [],
        "isActive": true
      },
      "after": {
        "slug": "patek-philippe-nautilus-aci1n",
        "sku": "SKU-d78621",
        "images": [],
        "variants": [
          {
            "sku": "SKU-d78621",
            "price": 1500000000,
            "title": "Patek Philippe Nautilus",
            "isDefault": true
          }
        ],
        "isActive": true
      }
    },
    {
      "id": "6a0d8905d38ea5fe36d78622",
      "before": {
        "slug": "patek-philippe-nautilus-zatm7o",
        "images": [],
        "isActive": true
      },
      "after": {
        "slug": "patek-philippe-nautilus-zatm7o",
        "sku": "SKU-d78622",
        "images": [],
        "variants": [
          {
            "sku": "SKU-d78622",
            "price": 1500000000,
            "title": "Patek Philippe Nautilus",
            "isDefault": true
          }
        ],
        "isActive": true
      }
    },
    {
      "id": "6a0d8905d38ea5fe36d78623",
      "before": {
        "slug": "patek-philippe-aquanaut-0l5poh",
        "images": [],
        "isActive": true
      },
      "after": {
        "slug": "patek-philippe-aquanaut-0l5poh",
        "sku": "SKU-d78623",
        "images": [],
        "variants": [
          {
            "sku": "SKU-d78623",
            "price": 950000000,
            "title": "Patek Philippe Aquanaut",
            "isDefault": true
          }
        ],
        "isActive": true
      }
    },
    {
      "id": "6a0d8905d38ea5fe36d78624",
      "before": {
        "slug": "patek-philippe-aquanaut-l6bp4",
        "images": [],
        "isActive": true
      },
      "after": {
        "slug": "patek-philippe-aquanaut-l6bp4",
        "sku": "SKU-d78624",
        "images": [],
        "variants": [
          {
            "sku": "SKU-d78624",
            "price": 1235000000,
            "title": "Patek Philippe Aquanaut",
            "isDefault": true
          }
        ],
        "isActive": true
      }
    },
    {
      "id": "6a0d8905d38ea5fe36d78625",
      "before": {
        "slug": "patek-philippe-aquanaut-t2zp3e",
        "images": [],
        "isActive": true
      },
      "after": {
        "slug": "patek-philippe-aquanaut-t2zp3e",
        "sku": "SKU-d78625",
        "images": [],
        "variants": [
          {
            "sku": "SKU-d78625",
            "price": 950000000,
            "title": "Patek Philippe Aquanaut",
            "isDefault": true
          }
        ],
        "isActive": true
      }
    },
    {
      "id": "6a0d8905d38ea5fe36d78626",
      "before": {
        "slug": "patek-philippe-aquanaut-jt21ah",
        "images": [],
        "isActive": true
      },
      "after": {
        "slug": "patek-philippe-aquanaut-jt21ah",
        "sku": "SKU-d78626",
        "images": [],
        "variants": [
          {
            "sku": "SKU-d78626",
            "price": 1235000000,
            "title": "Patek Philippe Aquanaut",
            "isDefault": true
          }
        ],
        "isActive": true
      }
    },
    {
      "id": "6a0d8905d38ea5fe36d78627",
      "before": {
        "slug": "patek-philippe-aquanaut-i1fopv",
        "images": [],
        "isActive": true
      },
      "after": {
        "slug": "patek-philippe-aquanaut-i1fopv",
        "sku": "SKU-d78627",
        "images": [],
        "variants": [
          {
            "sku": "SKU-d78627",
            "price": 950000000,
            "title": "Patek Philippe Aquanaut",
            "isDefault": true
          }
        ],
        "isActive": true
      }
    },
    {
      "id": "6a0d8905d38ea5fe36d78628",
      "before": {
        "slug": "patek-philippe-aquanaut-wvpflb",
        "images": [],
        "isActive": true
      },
      "after": {
        "slug": "patek-philippe-aquanaut-wvpflb",
        "sku": "SKU-d78628",
        "images": [],
        "variants": [
          {
            "sku": "SKU-d78628",
            "price": 1235000000,
            "title": "Patek Philippe Aquanaut",
            "isDefault": true
          }
        ],
        "isActive": true
      }
    },
    {
      "id": "6a0d8905d38ea5fe36d78629",
      "before": {
        "slug": "patek-philippe-aquanaut-3d4zhmu",
        "images": [],
        "isActive": true
      },
      "after": {
        "slug": "patek-philippe-aquanaut-3d4zhmu",
        "sku": "SKU-d78629",
        "images": [],
        "variants": [
          {
            "sku": "SKU-d78629",
            "price": 950000000,
            "title": "Patek Philippe Aquanaut",
            "isDefault": true
          }
        ],
        "isActive": true
      }
    },
    {
      "id": "6a0d8905d38ea5fe36d7862a",
      "before": {
        "slug": "patek-philippe-aquanaut-uh8ndf",
        "images": [],
        "isActive": true
      },
      "after": {
        "slug": "patek-philippe-aquanaut-uh8ndf",
        "sku": "SKU-d7862a",
        "images": [],
        "variants": [
          {
            "sku": "SKU-d7862a",
            "price": 1235000000,
            "title": "Patek Philippe Aquanaut",
            "isDefault": true
          }
        ],
        "isActive": true
      }
    },
    {
      "id": "6a0d8905d38ea5fe36d7862b",
      "before": {
        "slug": "patek-philippe-calatrava-lo92xn",
        "images": [],
        "isActive": true
      },
      "after": {
        "slug": "patek-philippe-calatrava-lo92xn",
        "sku": "SKU-d7862b",
        "images": [],
        "variants": [
          {
            "sku": "SKU-d7862b",
            "price": 975000000,
            "title": "Patek Philippe Calatrava",
            "isDefault": true
          }
        ],
        "isActive": true
      }
    },
    {
      "id": "6a0d8905d38ea5fe36d7862c",
      "before": {
        "slug": "patek-philippe-calatrava-9rhchb",
        "images": [],
        "isActive": true
      },
      "after": {
        "slug": "patek-philippe-calatrava-9rhchb",
        "sku": "SKU-d7862c",
        "images": [],
        "variants": [
          {
            "sku": "SKU-d7862c",
            "price": 975000000,
            "title": "Patek Philippe Calatrava",
            "isDefault": true
          }
        ],
        "isActive": true
      }
    },
    {
      "id": "6a0d8905d38ea5fe36d7862d",
      "before": {
        "slug": "patek-philippe-calatrava-v30lz",
        "images": [],
        "isActive": true
      },
      "after": {
        "slug": "patek-philippe-calatrava-v30lz",
        "sku": "SKU-d7862d",
        "images": [],
        "variants": [
          {
            "sku": "SKU-d7862d",
            "price": 975000000,
            "title": "Patek Philippe Calatrava",
            "isDefault": true
          }
        ],
        "isActive": true
      }
    },
    {
      "id": "6a0d8905d38ea5fe36d7862e",
      "before": {
        "slug": "patek-philippe-calatrava-7xhsjrf",
        "images": [],
        "isActive": true
      },
      "after": {
        "slug": "patek-philippe-calatrava-7xhsjrf",
        "sku": "SKU-d7862e",
        "images": [],
        "variants": [
          {
            "sku": "SKU-d7862e",
            "price": 975000000,
            "title": "Patek Philippe Calatrava",
            "isDefault": true
          }
        ],
        "isActive": true
      }
    },
    {
      "id": "6a0d8905d38ea5fe36d7862f",
      "before": {
        "slug": "patek-philippe-calatrava-uyk7sm",
        "images": [],
        "isActive": true
      },
      "after": {
        "slug": "patek-philippe-calatrava-uyk7sm",
        "sku": "SKU-d7862f",
        "images": [],
        "variants": [
          {
            "sku": "SKU-d7862f",
            "price": 975000000,
            "title": "Patek Philippe Calatrava",
            "isDefault": true
          }
        ],
        "isActive": true
      }
    },
    {
      "id": "6a0d8905d38ea5fe36d78630",
      "before": {
        "slug": "patek-philippe-calatrava-oycdap",
        "images": [],
        "isActive": true
      },
      "after": {
        "slug": "patek-philippe-calatrava-oycdap",
        "sku": "SKU-d78630",
        "images": [],
        "variants": [
          {
            "sku": "SKU-d78630",
            "price": 975000000,
            "title": "Patek Philippe Calatrava",
            "isDefault": true
          }
        ],
        "isActive": true
      }
    },
    {
      "id": "6a0d8905d38ea5fe36d78631",
      "before": {
        "slug": "patek-philippe-nautilus-chronograph-6aqekr",
        "images": [],
        "isActive": true
      },
      "after": {
        "slug": "patek-philippe-nautilus-chronograph-6aqekr",
        "sku": "SKU-d78631",
        "images": [],
        "variants": [
          {
            "sku": "SKU-d78631",
            "price": 2860000000,
            "title": "Patek Philippe Nautilus Chronograph",
            "isDefault": true
          }
        ],
        "isActive": true
      }
    },
    {
      "id": "6a0d8905d38ea5fe36d78632",
      "before": {
        "slug": "patek-philippe-nautilus-chronograph-46hosu",
        "images": [],
        "isActive": true
      },
      "after": {
        "slug": "patek-philippe-nautilus-chronograph-46hosu",
        "sku": "SKU-d78632",
        "images": [],
        "variants": [
          {
            "sku": "SKU-d78632",
            "price": 2860000000,
            "title": "Patek Philippe Nautilus Chronograph",
            "isDefault": true
          }
        ],
        "isActive": true
      }
    },
    {
      "id": "6a0d8905d38ea5fe36d7867d",
      "before": {
        "slug": "hublot-classic-fusion-9wpe8n",
        "images": [],
        "isActive": true
      },
      "after": {
        "slug": "hublot-classic-fusion-9wpe8n",
        "sku": "SKU-d7867d",
        "images": [],
        "variants": [
          {
            "sku": "SKU-d7867d",
            "price": 189000000,
            "title": "Hublot Classic Fusion",
            "isDefault": true
          }
        ],
        "isActive": true
      }
    },
    {
      "id": "6a0d8905d38ea5fe36d7867e",
      "before": {
        "slug": "hublot-classic-fusion-a6uzx",
        "images": [],
        "isActive": true
      },
      "after": {
        "slug": "hublot-classic-fusion-a6uzx",
        "sku": "SKU-d7867e",
        "images": [],
        "variants": [
          {
            "sku": "SKU-d7867e",
            "price": 243000000,
            "title": "Hublot Classic Fusion",
            "isDefault": true
          }
        ],
        "isActive": true
      }
    },
    {
      "id": "6a0d8905d38ea5fe36d7867f",
      "before": {
        "slug": "hublot-classic-fusion-xxqilq",
        "images": [],
        "isActive": true
      },
      "after": {
        "slug": "hublot-classic-fusion-xxqilq",
        "sku": "SKU-d7867f",
        "images": [],
        "variants": [
          {
            "sku": "SKU-d7867f",
            "price": 243000000,
            "title": "Hublot Classic Fusion",
            "isDefault": true
          }
        ],
        "isActive": true
      }
    },
    {
      "id": "6a0d8905d38ea5fe36d78680",
      "before": {
        "slug": "hublot-classic-fusion-dln7s5",
        "images": [],
        "isActive": true
      },
      "after": {
        "slug": "hublot-classic-fusion-dln7s5",
        "sku": "SKU-d78680",
        "images": [],
        "variants": [
          {
            "sku": "SKU-d78680",
            "price": 180000000,
            "title": "Hublot Classic Fusion",
            "isDefault": true
          }
        ],
        "isActive": true
      }
    },
    {
      "id": "6a0d8905d38ea5fe36d78681",
      "before": {
        "slug": "hublot-classic-fusion-dut37",
        "images": [],
        "isActive": true
      },
      "after": {
        "slug": "hublot-classic-fusion-dut37",
        "sku": "SKU-d78681",
        "images": [],
        "variants": [
          {
            "sku": "SKU-d78681",
            "price": 234000000,
            "title": "Hublot Classic Fusion",
            "isDefault": true
          }
        ],
        "isActive": true
      }
    },
    {
      "id": "6a0d8905d38ea5fe36d78682",
      "before": {
        "slug": "hublot-classic-fusion-9jwla",
        "images": [],
        "isActive": true
      },
      "after": {
        "slug": "hublot-classic-fusion-9jwla",
        "sku": "SKU-d78682",
        "images": [],
        "variants": [
          {
            "sku": "SKU-d78682",
            "price": 234000000,
            "title": "Hublot Classic Fusion",
            "isDefault": true
          }
        ],
        "isActive": true
      }
    },
    {
      "id": "6a0d8905d38ea5fe36d78683",
      "before": {
        "slug": "hublot-classic-fusion-f2vgka",
        "images": [],
        "isActive": true
      },
      "after": {
        "slug": "hublot-classic-fusion-f2vgka",
        "sku": "SKU-d78683",
        "images": [],
        "variants": [
          {
            "sku": "SKU-d78683",
            "price": 180000000,
            "title": "Hublot Classic Fusion",
            "isDefault": true
          }
        ],
        "isActive": true
      }
    },
    {
      "id": "6a0d8905d38ea5fe36d78684",
      "before": {
        "slug": "hublot-classic-fusion-vir9dg",
        "images": [],
        "isActive": true
      },
      "after": {
        "slug": "hublot-classic-fusion-vir9dg",
        "sku": "SKU-d78684",
        "images": [],
        "variants": [
          {
            "sku": "SKU-d78684",
            "price": 234000000,
            "title": "Hublot Classic Fusion",
            "isDefault": true
          }
        ],
        "isActive": true
      }
    },
    {
      "id": "6a0d8905d38ea5fe36d78685",
      "before": {
        "slug": "hublot-classic-fusion-2xr87t",
        "images": [],
        "isActive": true
      },
      "after": {
        "slug": "hublot-classic-fusion-2xr87t",
        "sku": "SKU-d78685",
        "images": [],
        "variants": [
          {
            "sku": "SKU-d78685",
            "price": 234000000,
            "title": "Hublot Classic Fusion",
            "isDefault": true
          }
        ],
        "isActive": true
      }
    },
    {
      "id": "6a0d8905d38ea5fe36d78686",
      "before": {
        "slug": "hublot-classic-fusion-7r1nxp",
        "images": [],
        "isActive": true
      },
      "after": {
        "slug": "hublot-classic-fusion-7r1nxp",
        "sku": "SKU-d78686",
        "images": [],
        "variants": [
          {
            "sku": "SKU-d78686",
            "price": 189000000,
            "title": "Hublot Classic Fusion",
            "isDefault": true
          }
        ],
        "isActive": true
      }
    },
    {
      "id": "6a0d8905d38ea5fe36d78687",
      "before": {
        "slug": "hublot-classic-fusion-n199af",
        "images": [],
        "isActive": true
      },
      "after": {
        "slug": "hublot-classic-fusion-n199af",
        "sku": "SKU-d78687",
        "images": [],
        "variants": [
          {
            "sku": "SKU-d78687",
            "price": 243000000,
            "title": "Hublot Classic Fusion",
            "isDefault": true
          }
        ],
        "isActive": true
      }
    },
    {
      "id": "6a0d8905d38ea5fe36d78688",
      "before": {
        "slug": "hublot-classic-fusion-mqoed",
        "images": [],
        "isActive": true
      },
      "after": {
        "slug": "hublot-classic-fusion-mqoed",
        "sku": "SKU-d78688",
        "images": [],
        "variants": [
          {
            "sku": "SKU-d78688",
            "price": 243000000,
            "title": "Hublot Classic Fusion",
            "isDefault": true
          }
        ],
        "isActive": true
      }
    },
    {
      "id": "6a0d8905d38ea5fe36d78689",
      "before": {
        "slug": "hublot-classic-fusion-6dgv8",
        "images": [],
        "isActive": true
      },
      "after": {
        "slug": "hublot-classic-fusion-6dgv8",
        "sku": "SKU-d78689",
        "images": [],
        "variants": [
          {
            "sku": "SKU-d78689",
            "price": 180000000,
            "title": "Hublot Classic Fusion",
            "isDefault": true
          }
        ],
        "isActive": true
      }
    },
    {
      "id": "6a0d8905d38ea5fe36d7868a",
      "before": {
        "slug": "hublot-classic-fusion-utzg5p",
        "images": [],
        "isActive": true
      },
      "after": {
        "slug": "hublot-classic-fusion-utzg5p",
        "sku": "SKU-d7868a",
        "images": [],
        "variants": [
          {
            "sku": "SKU-d7868a",
            "price": 234000000,
            "title": "Hublot Classic Fusion",
            "isDefault": true
          }
        ],
        "isActive": true
      }
    },
    {
      "id": "6a0d8905d38ea5fe36d7868b",
      "before": {
        "slug": "hublot-classic-fusion-gd4r9",
        "images": [],
        "isActive": true
      },
      "after": {
        "slug": "hublot-classic-fusion-gd4r9",
        "sku": "SKU-d7868b",
        "images": [],
        "variants": [
          {
            "sku": "SKU-d7868b",
            "price": 234000000,
            "title": "Hublot Classic Fusion",
            "isDefault": true
          }
        ],
        "isActive": true
      }
    },
    {
      "id": "6a0d8905d38ea5fe36d7868c",
      "before": {
        "slug": "hublot-classic-fusion-r4j0o9",
        "images": [],
        "isActive": true
      },
      "after": {
        "slug": "hublot-classic-fusion-r4j0o9",
        "sku": "SKU-d7868c",
        "images": [],
        "variants": [
          {
            "sku": "SKU-d7868c",
            "price": 180000000,
            "title": "Hublot Classic Fusion",
            "isDefault": true
          }
        ],
        "isActive": true
      }
    },
    {
      "id": "6a0d8905d38ea5fe36d7868d",
      "before": {
        "slug": "hublot-classic-fusion-wg1gx",
        "images": [],
        "isActive": true
      },
      "after": {
        "slug": "hublot-classic-fusion-wg1gx",
        "sku": "SKU-d7868d",
        "images": [],
        "variants": [
          {
            "sku": "SKU-d7868d",
            "price": 234000000,
            "title": "Hublot Classic Fusion",
            "isDefault": true
          }
        ],
        "isActive": true
      }
    },
    {
      "id": "6a0d8905d38ea5fe36d7868e",
      "before": {
        "slug": "hublot-classic-fusion-4v2eqb",
        "images": [],
        "isActive": true
      },
      "after": {
        "slug": "hublot-classic-fusion-4v2eqb",
        "sku": "SKU-d7868e",
        "images": [],
        "variants": [
          {
            "sku": "SKU-d7868e",
            "price": 234000000,
            "title": "Hublot Classic Fusion",
            "isDefault": true
          }
        ],
        "isActive": true
      }
    },
    {
      "id": "6a0d8905d38ea5fe36d7868f",
      "before": {
        "slug": "hublot-classic-fusion-0o1h9h",
        "images": [],
        "isActive": true
      },
      "after": {
        "slug": "hublot-classic-fusion-0o1h9h",
        "sku": "SKU-d7868f",
        "images": [],
        "variants": [
          {
            "sku": "SKU-d7868f",
            "price": 189000000,
            "title": "Hublot Classic Fusion",
            "isDefault": true
          }
        ],
        "isActive": true
      }
    },
    {
      "id": "6a0d8905d38ea5fe36d78690",
      "before": {
        "slug": "hublot-classic-fusion-e79mgg",
        "images": [],
        "isActive": true
      },
      "after": {
        "slug": "hublot-classic-fusion-e79mgg",
        "sku": "SKU-d78690",
        "images": [],
        "variants": [
          {
            "sku": "SKU-d78690",
            "price": 243000000,
            "title": "Hublot Classic Fusion",
            "isDefault": true
          }
        ],
        "isActive": true
      }
    },
    {
      "id": "6a0d8905d38ea5fe36d78691",
      "before": {
        "slug": "hublot-classic-fusion-w64f5",
        "images": [],
        "isActive": true
      },
      "after": {
        "slug": "hublot-classic-fusion-w64f5",
        "sku": "SKU-d78691",
        "images": [],
        "variants": [
          {
            "sku": "SKU-d78691",
            "price": 243000000,
            "title": "Hublot Classic Fusion",
            "isDefault": true
          }
        ],
        "isActive": true
      }
    },
    {
      "id": "6a0d8905d38ea5fe36d78692",
      "before": {
        "slug": "hublot-classic-fusion-niz6p",
        "images": [],
        "isActive": true
      },
      "after": {
        "slug": "hublot-classic-fusion-niz6p",
        "sku": "SKU-d78692",
        "images": [],
        "variants": [
          {
            "sku": "SKU-d78692",
            "price": 180000000,
            "title": "Hublot Classic Fusion",
            "isDefault": true
          }
        ],
        "isActive": true
      }
    },
    {
      "id": "6a0d8905d38ea5fe36d78693",
      "before": {
        "slug": "hublot-classic-fusion-elcq6j",
        "images": [],
        "isActive": true
      },
      "after": {
        "slug": "hublot-classic-fusion-elcq6j",
        "sku": "SKU-d78693",
        "images": [],
        "variants": [
          {
            "sku": "SKU-d78693",
            "price": 234000000,
            "title": "Hublot Classic Fusion",
            "isDefault": true
          }
        ],
        "isActive": true
      }
    },
    {
      "id": "6a0d8905d38ea5fe36d78694",
      "before": {
        "slug": "hublot-classic-fusion-9hiyr",
        "images": [],
        "isActive": true
      },
      "after": {
        "slug": "hublot-classic-fusion-9hiyr",
        "sku": "SKU-d78694",
        "images": [],
        "variants": [
          {
            "sku": "SKU-d78694",
            "price": 234000000,
            "title": "Hublot Classic Fusion",
            "isDefault": true
          }
        ],
        "isActive": true
      }
    },
    {
      "id": "6a0d8905d38ea5fe36d78695",
      "before": {
        "slug": "hublot-classic-fusion-toebdn",
        "images": [],
        "isActive": true
      },
      "after": {
        "slug": "hublot-classic-fusion-toebdn",
        "sku": "SKU-d78695",
        "images": [],
        "variants": [
          {
            "sku": "SKU-d78695",
            "price": 180000000,
            "title": "Hublot Classic Fusion",
            "isDefault": true
          }
        ],
        "isActive": true
      }
    },
    {
      "id": "6a0d8905d38ea5fe36d78696",
      "before": {
        "slug": "hublot-classic-fusion-m018w8",
        "images": [],
        "isActive": true
      },
      "after": {
        "slug": "hublot-classic-fusion-m018w8",
        "sku": "SKU-d78696",
        "images": [],
        "variants": [
          {
            "sku": "SKU-d78696",
            "price": 234000000,
            "title": "Hublot Classic Fusion",
            "isDefault": true
          }
        ],
        "isActive": true
      }
    },
    {
      "id": "6a0d8905d38ea5fe36d78697",
      "before": {
        "slug": "hublot-classic-fusion-zp3cn",
        "images": [],
        "isActive": true
      },
      "after": {
        "slug": "hublot-classic-fusion-zp3cn",
        "sku": "SKU-d78697",
        "images": [],
        "variants": [
          {
            "sku": "SKU-d78697",
            "price": 234000000,
            "title": "Hublot Classic Fusion",
            "isDefault": true
          }
        ],
        "isActive": true
      }
    },
    {
      "id": "6a0d8905d38ea5fe36d78698",
      "before": {
        "slug": "hublot-classic-fusion-0yf1z9",
        "images": [],
        "isActive": true
      },
      "after": {
        "slug": "hublot-classic-fusion-0yf1z9",
        "sku": "SKU-d78698",
        "images": [],
        "variants": [
          {
            "sku": "SKU-d78698",
            "price": 189000000,
            "title": "Hublot Classic Fusion",
            "isDefault": true
          }
        ],
        "isActive": true
      }
    },
    {
      "id": "6a0d8905d38ea5fe36d78699",
      "before": {
        "slug": "hublot-classic-fusion-kbzv8",
        "images": [],
        "isActive": true
      },
      "after": {
        "slug": "hublot-classic-fusion-kbzv8",
        "sku": "SKU-d78699",
        "images": [],
        "variants": [
          {
            "sku": "SKU-d78699",
            "price": 243000000,
            "title": "Hublot Classic Fusion",
            "isDefault": true
          }
        ],
        "isActive": true
      }
    },
    {
      "id": "6a0d8905d38ea5fe36d7869a",
      "before": {
        "slug": "hublot-classic-fusion-xq4ii",
        "images": [],
        "isActive": true
      },
      "after": {
        "slug": "hublot-classic-fusion-xq4ii",
        "sku": "SKU-d7869a",
        "images": [],
        "variants": [
          {
            "sku": "SKU-d7869a",
            "price": 243000000,
            "title": "Hublot Classic Fusion",
            "isDefault": true
          }
        ],
        "isActive": true
      }
    },
    {
      "id": "6a0d8905d38ea5fe36d7869b",
      "before": {
        "slug": "hublot-classic-fusion-creypb",
        "images": [],
        "isActive": true
      },
      "after": {
        "slug": "hublot-classic-fusion-creypb",
        "sku": "SKU-d7869b",
        "images": [],
        "variants": [
          {
            "sku": "SKU-d7869b",
            "price": 180000000,
            "title": "Hublot Classic Fusion",
            "isDefault": true
          }
        ],
        "isActive": true
      }
    },
    {
      "id": "6a0d8905d38ea5fe36d7869c",
      "before": {
        "slug": "hublot-classic-fusion-5hsio",
        "images": [],
        "isActive": true
      },
      "after": {
        "slug": "hublot-classic-fusion-5hsio",
        "sku": "SKU-d7869c",
        "images": [],
        "variants": [
          {
            "sku": "SKU-d7869c",
            "price": 234000000,
            "title": "Hublot Classic Fusion",
            "isDefault": true
          }
        ],
        "isActive": true
      }
    },
    {
      "id": "6a0d8905d38ea5fe36d7869d",
      "before": {
        "slug": "hublot-classic-fusion-hh51lo",
        "images": [],
        "isActive": true
      },
      "after": {
        "slug": "hublot-classic-fusion-hh51lo",
        "sku": "SKU-d7869d",
        "images": [],
        "variants": [
          {
            "sku": "SKU-d7869d",
            "price": 234000000,
            "title": "Hublot Classic Fusion",
            "isDefault": true
          }
        ],
        "isActive": true
      }
    },
    {
      "id": "6a0d8905d38ea5fe36d7869e",
      "before": {
        "slug": "hublot-classic-fusion-am2fq",
        "images": [],
        "isActive": true
      },
      "after": {
        "slug": "hublot-classic-fusion-am2fq",
        "sku": "SKU-d7869e",
        "images": [],
        "variants": [
          {
            "sku": "SKU-d7869e",
            "price": 180000000,
            "title": "Hublot Classic Fusion",
            "isDefault": true
          }
        ],
        "isActive": true
      }
    },
    {
      "id": "6a0d8905d38ea5fe36d7869f",
      "before": {
        "slug": "hublot-classic-fusion-owzku6",
        "images": [],
        "isActive": true
      },
      "after": {
        "slug": "hublot-classic-fusion-owzku6",
        "sku": "SKU-d7869f",
        "images": [],
        "variants": [
          {
            "sku": "SKU-d7869f",
            "price": 234000000,
            "title": "Hublot Classic Fusion",
            "isDefault": true
          }
        ],
        "isActive": true
      }
    },
    {
      "id": "6a0d8905d38ea5fe36d786a0",
      "before": {
        "slug": "hublot-classic-fusion-3wygd3o",
        "images": [],
        "isActive": true
      },
      "after": {
        "slug": "hublot-classic-fusion-3wygd3o",
        "sku": "SKU-d786a0",
        "images": [],
        "variants": [
          {
            "sku": "SKU-d786a0",
            "price": 234000000,
            "title": "Hublot Classic Fusion",
            "isDefault": true
          }
        ],
        "isActive": true
      }
    },
    {
      "id": "6a0d8905d38ea5fe36d786a1",
      "before": {
        "slug": "hublot-big-bang-unico-wtjwyq",
        "images": [],
        "isActive": true
      },
      "after": {
        "slug": "hublot-big-bang-unico-wtjwyq",
        "sku": "SKU-d786a1",
        "images": [],
        "variants": [
          {
            "sku": "SKU-d786a1",
            "price": 624000000,
            "title": "Hublot Big Bang Unico",
            "isDefault": true
          }
        ],
        "isActive": true
      }
    },
    {
      "id": "6a0d8905d38ea5fe36d786a2",
      "before": {
        "slug": "hublot-big-bang-unico-87ibf",
        "images": [],
        "isActive": true
      },
      "after": {
        "slug": "hublot-big-bang-unico-87ibf",
        "sku": "SKU-d786a2",
        "images": [],
        "variants": [
          {
            "sku": "SKU-d786a2",
            "price": 624000000,
            "title": "Hublot Big Bang Unico",
            "isDefault": true
          }
        ],
        "isActive": true
      }
    },
    {
      "id": "6a0d8905d38ea5fe36d786a3",
      "before": {
        "slug": "hublot-big-bang-unico-mblba7j",
        "images": [],
        "isActive": true
      },
      "after": {
        "slug": "hublot-big-bang-unico-mblba7j",
        "sku": "SKU-d786a3",
        "images": [],
        "variants": [
          {
            "sku": "SKU-d786a3",
            "price": 648000000,
            "title": "Hublot Big Bang Unico",
            "isDefault": true
          }
        ],
        "isActive": true
      }
    },
    {
      "id": "6a0d8905d38ea5fe36d786a4",
      "before": {
        "slug": "hublot-big-bang-unico-h5nhc6",
        "images": [],
        "isActive": true
      },
      "after": {
        "slug": "hublot-big-bang-unico-h5nhc6",
        "sku": "SKU-d786a4",
        "images": [],
        "variants": [
          {
            "sku": "SKU-d786a4",
            "price": 648000000,
            "title": "Hublot Big Bang Unico",
            "isDefault": true
          }
        ],
        "isActive": true
      }
    },
    {
      "id": "6a0d8905d38ea5fe36d786a5",
      "before": {
        "slug": "hublot-big-bang-unico-k6at8q",
        "images": [],
        "isActive": true
      },
      "after": {
        "slug": "hublot-big-bang-unico-k6at8q",
        "sku": "SKU-d786a5",
        "images": [],
        "variants": [
          {
            "sku": "SKU-d786a5",
            "price": 624000000,
            "title": "Hublot Big Bang Unico",
            "isDefault": true
          }
        ],
        "isActive": true
      }
    },
    {
      "id": "6a0d8905d38ea5fe36d786a6",
      "before": {
        "slug": "hublot-big-bang-unico-dpvxah",
        "images": [],
        "isActive": true
      },
      "after": {
        "slug": "hublot-big-bang-unico-dpvxah",
        "sku": "SKU-d786a6",
        "images": [],
        "variants": [
          {
            "sku": "SKU-d786a6",
            "price": 624000000,
            "title": "Hublot Big Bang Unico",
            "isDefault": true
          }
        ],
        "isActive": true
      }
    },
    {
      "id": "6a0d8905d38ea5fe36d786a7",
      "before": {
        "slug": "hublot-big-bang-unico-sjnpf",
        "images": [],
        "isActive": true
      },
      "after": {
        "slug": "hublot-big-bang-unico-sjnpf",
        "sku": "SKU-d786a7",
        "images": [],
        "variants": [
          {
            "sku": "SKU-d786a7",
            "price": 648000000,
            "title": "Hublot Big Bang Unico",
            "isDefault": true
          }
        ],
        "isActive": true
      }
    },
    {
      "id": "6a0d8905d38ea5fe36d786a8",
      "before": {
        "slug": "hublot-big-bang-unico-0lvoql",
        "images": [],
        "isActive": true
      },
      "after": {
        "slug": "hublot-big-bang-unico-0lvoql",
        "sku": "SKU-d786a8",
        "images": [],
        "variants": [
          {
            "sku": "SKU-d786a8",
            "price": 648000000,
            "title": "Hublot Big Bang Unico",
            "isDefault": true
          }
        ],
        "isActive": true
      }
    },
    {
      "id": "6a0d8905d38ea5fe36d786a9",
      "before": {
        "slug": "hublot-spirit-of-big-bang-9i51lh",
        "images": [],
        "isActive": true
      },
      "after": {
        "slug": "hublot-spirit-of-big-bang-9i51lh",
        "sku": "SKU-d786a9",
        "images": [],
        "variants": [
          {
            "sku": "SKU-d786a9",
            "price": 577500000,
            "title": "Hublot Spirit of Big Bang",
            "isDefault": true
          }
        ],
        "isActive": true
      }
    },
    {
      "id": "6a0d8905d38ea5fe36d786aa",
      "before": {
        "slug": "hublot-spirit-of-big-bang-8d8lep",
        "images": [],
        "isActive": true
      },
      "after": {
        "slug": "hublot-spirit-of-big-bang-8d8lep",
        "sku": "SKU-d786aa",
        "images": [],
        "variants": [
          {
            "sku": "SKU-d786aa",
            "price": 742500000,
            "title": "Hublot Spirit of Big Bang",
            "isDefault": true
          }
        ],
        "isActive": true
      }
    },
    {
      "id": "6a0d8905d38ea5fe36d786ab",
      "before": {
        "slug": "hublot-spirit-of-big-bang-khda3",
        "images": [],
        "isActive": true
      },
      "after": {
        "slug": "hublot-spirit-of-big-bang-khda3",
        "sku": "SKU-d786ab",
        "images": [],
        "variants": [
          {
            "sku": "SKU-d786ab",
            "price": 550000000,
            "title": "Hublot Spirit of Big Bang",
            "isDefault": true
          }
        ],
        "isActive": true
      }
    },
    {
      "id": "6a0d8905d38ea5fe36d786ac",
      "before": {
        "slug": "hublot-spirit-of-big-bang-l1fkod",
        "images": [],
        "isActive": true
      },
      "after": {
        "slug": "hublot-spirit-of-big-bang-l1fkod",
        "sku": "SKU-d786ac",
        "images": [],
        "variants": [
          {
            "sku": "SKU-d786ac",
            "price": 715000000,
            "title": "Hublot Spirit of Big Bang",
            "isDefault": true
          }
        ],
        "isActive": true
      }
    },
    {
      "id": "6a0d8905d38ea5fe36d786ad",
      "before": {
        "slug": "hublot-spirit-of-big-bang-06hued",
        "images": [],
        "isActive": true
      },
      "after": {
        "slug": "hublot-spirit-of-big-bang-06hued",
        "sku": "SKU-d786ad",
        "images": [],
        "variants": [
          {
            "sku": "SKU-d786ad",
            "price": 577500000,
            "title": "Hublot Spirit of Big Bang",
            "isDefault": true
          }
        ],
        "isActive": true
      }
    },
    {
      "id": "6a0d8905d38ea5fe36d786ae",
      "before": {
        "slug": "hublot-spirit-of-big-bang-9qya5",
        "images": [],
        "isActive": true
      },
      "after": {
        "slug": "hublot-spirit-of-big-bang-9qya5",
        "sku": "SKU-d786ae",
        "images": [],
        "variants": [
          {
            "sku": "SKU-d786ae",
            "price": 742500000,
            "title": "Hublot Spirit of Big Bang",
            "isDefault": true
          }
        ],
        "isActive": true
      }
    },
    {
      "id": "6a0d8905d38ea5fe36d786af",
      "before": {
        "slug": "hublot-spirit-of-big-bang-oy243l",
        "images": [],
        "isActive": true
      },
      "after": {
        "slug": "hublot-spirit-of-big-bang-oy243l",
        "sku": "SKU-d786af",
        "images": [],
        "variants": [
          {
            "sku": "SKU-d786af",
            "price": 550000000,
            "title": "Hublot Spirit of Big Bang",
            "isDefault": true
          }
        ],
        "isActive": true
      }
    },
    {
      "id": "6a0d8905d38ea5fe36d786b0",
      "before": {
        "slug": "hublot-spirit-of-big-bang-qej5og",
        "images": [],
        "isActive": true
      },
      "after": {
        "slug": "hublot-spirit-of-big-bang-qej5og",
        "sku": "SKU-d786b0",
        "images": [],
        "variants": [
          {
            "sku": "SKU-d786b0",
            "price": 715000000,
            "title": "Hublot Spirit of Big Bang",
            "isDefault": true
          }
        ],
        "isActive": true
      }
    },
    {
      "id": "6a0d8905d38ea5fe36d785eb",
      "before": {
        "slug": "omega-speedmaster-moonwatch-professional-cvlth8",
        "images": [],
        "isActive": true
      },
      "after": {
        "slug": "omega-speedmaster-moonwatch-professional-cvlth8",
        "sku": "SKU-d785eb",
        "images": [],
        "variants": [
          {
            "sku": "SKU-d785eb",
            "price": 165000000,
            "title": "Omega Speedmaster Moonwatch Professional",
            "isDefault": true
          }
        ],
        "isActive": true
      }
    },
    {
      "id": "6a0d8905d38ea5fe36d785ec",
      "before": {
        "slug": "omega-speedmaster-moonwatch-professional-426usi",
        "images": [],
        "isActive": true
      },
      "after": {
        "slug": "omega-speedmaster-moonwatch-professional-426usi",
        "sku": "SKU-d785ec",
        "images": [],
        "variants": [
          {
            "sku": "SKU-d785ec",
            "price": 165000000,
            "title": "Omega Speedmaster Moonwatch Professional",
            "isDefault": true
          }
        ],
        "isActive": true
      }
    },
    {
      "id": "6a0d8905d38ea5fe36d785ed",
      "before": {
        "slug": "omega-seamaster-diver-300m-vzxigi",
        "images": [],
        "isActive": true
      },
      "after": {
        "slug": "omega-seamaster-diver-300m-vzxigi",
        "sku": "SKU-d785ed",
        "images": [],
        "variants": [
          {
            "sku": "SKU-d785ed",
            "price": 135000000,
            "title": "Omega Seamaster Diver 300M",
            "isDefault": true
          }
        ],
        "isActive": true
      }
    },
    {
      "id": "6a0d8905d38ea5fe36d785ee",
      "before": {
        "slug": "omega-seamaster-diver-300m-h0xqid",
        "images": [],
        "isActive": true
      },
      "after": {
        "slug": "omega-seamaster-diver-300m-h0xqid",
        "sku": "SKU-d785ee",
        "images": [],
        "variants": [
          {
            "sku": "SKU-d785ee",
            "price": 135000000,
            "title": "Omega Seamaster Diver 300M",
            "isDefault": true
          }
        ],
        "isActive": true
      }
    },
    {
      "id": "6a0d8905d38ea5fe36d785ef",
      "before": {
        "slug": "omega-seamaster-diver-300m-tqhgds",
        "images": [],
        "isActive": true
      },
      "after": {
        "slug": "omega-seamaster-diver-300m-tqhgds",
        "sku": "SKU-d785ef",
        "images": [],
        "variants": [
          {
            "sku": "SKU-d785ef",
            "price": 135000000,
            "title": "Omega Seamaster Diver 300M",
            "isDefault": true
          }
        ],
        "isActive": true
      }
    },
    {
      "id": "6a0d8905d38ea5fe36d785f0",
      "before": {
        "slug": "omega-seamaster-diver-300m-326y8w",
        "images": [],
        "isActive": true
      },
      "after": {
        "slug": "omega-seamaster-diver-300m-326y8w",
        "sku": "SKU-d785f0",
        "images": [],
        "variants": [
          {
            "sku": "SKU-d785f0",
            "price": 135000000,
            "title": "Omega Seamaster Diver 300M",
            "isDefault": true
          }
        ],
        "isActive": true
      }
    },
    {
      "id": "6a0d8905d38ea5fe36d785f1",
      "before": {
        "slug": "omega-seamaster-diver-300m-hh84gg",
        "images": [],
        "isActive": true
      },
      "after": {
        "slug": "omega-seamaster-diver-300m-hh84gg",
        "sku": "SKU-d785f1",
        "images": [],
        "variants": [
          {
            "sku": "SKU-d785f1",
            "price": 135000000,
            "title": "Omega Seamaster Diver 300M",
            "isDefault": true
          }
        ],
        "isActive": true
      }
    },
    {
      "id": "6a0d8905d38ea5fe36d785f2",
      "before": {
        "slug": "omega-seamaster-diver-300m-kyu8kg",
        "images": [],
        "isActive": true
      },
      "after": {
        "slug": "omega-seamaster-diver-300m-kyu8kg",
        "sku": "SKU-d785f2",
        "images": [],
        "variants": [
          {
            "sku": "SKU-d785f2",
            "price": 135000000,
            "title": "Omega Seamaster Diver 300M",
            "isDefault": true
          }
        ],
        "isActive": true
      }
    },
    {
      "id": "6a0d8905d38ea5fe36d785f3",
      "before": {
        "slug": "omega-seamaster-diver-300m-x8wnj",
        "images": [],
        "isActive": true
      },
      "after": {
        "slug": "omega-seamaster-diver-300m-x8wnj",
        "sku": "SKU-d785f3",
        "images": [],
        "variants": [
          {
            "sku": "SKU-d785f3",
            "price": 135000000,
            "title": "Omega Seamaster Diver 300M",
            "isDefault": true
          }
        ],
        "isActive": true
      }
    },
    {
      "id": "6a0d8905d38ea5fe36d785f4",
      "before": {
        "slug": "omega-seamaster-diver-300m-0udl8b",
        "images": [],
        "isActive": true
      },
      "after": {
        "slug": "omega-seamaster-diver-300m-0udl8b",
        "sku": "SKU-d785f4",
        "images": [],
        "variants": [
          {
            "sku": "SKU-d785f4",
            "price": 135000000,
            "title": "Omega Seamaster Diver 300M",
            "isDefault": true
          }
        ],
        "isActive": true
      }
    },
    {
      "id": "6a0d8905d38ea5fe36d785f5",
      "before": {
        "slug": "omega-seamaster-diver-300m-h22wjg",
        "images": [],
        "isActive": true
      },
      "after": {
        "slug": "omega-seamaster-diver-300m-h22wjg",
        "sku": "SKU-d785f5",
        "images": [],
        "variants": [
          {
            "sku": "SKU-d785f5",
            "price": 135000000,
            "title": "Omega Seamaster Diver 300M",
            "isDefault": true
          }
        ],
        "isActive": true
      }
    },
    {
      "id": "6a0d8905d38ea5fe36d785f6",
      "before": {
        "slug": "omega-seamaster-diver-300m-w6loa",
        "images": [],
        "isActive": true
      },
      "after": {
        "slug": "omega-seamaster-diver-300m-w6loa",
        "sku": "SKU-d785f6",
        "images": [],
        "variants": [
          {
            "sku": "SKU-d785f6",
            "price": 135000000,
            "title": "Omega Seamaster Diver 300M",
            "isDefault": true
          }
        ],
        "isActive": true
      }
    },
    {
      "id": "6a0d8905d38ea5fe36d785f7",
      "before": {
        "slug": "omega-aqua-terra-150m-puv1yq",
        "images": [],
        "isActive": true
      },
      "after": {
        "slug": "omega-aqua-terra-150m-puv1yq",
        "sku": "SKU-d785f7",
        "images": [],
        "variants": [
          {
            "sku": "SKU-d785f7",
            "price": 145000000,
            "title": "Omega Aqua Terra 150M",
            "isDefault": true
          }
        ],
        "isActive": true
      }
    },
    {
      "id": "6a0d8905d38ea5fe36d785f8",
      "before": {
        "slug": "omega-aqua-terra-150m-zmt3e",
        "images": [],
        "isActive": true
      },
      "after": {
        "slug": "omega-aqua-terra-150m-zmt3e",
        "sku": "SKU-d785f8",
        "images": [],
        "variants": [
          {
            "sku": "SKU-d785f8",
            "price": 145000000,
            "title": "Omega Aqua Terra 150M",
            "isDefault": true
          }
        ],
        "isActive": true
      }
    },
    {
      "id": "6a0d8905d38ea5fe36d785f9",
      "before": {
        "slug": "omega-aqua-terra-150m-9lumt",
        "images": [],
        "isActive": true
      },
      "after": {
        "slug": "omega-aqua-terra-150m-9lumt",
        "sku": "SKU-d785f9",
        "images": [],
        "variants": [
          {
            "sku": "SKU-d785f9",
            "price": 145000000,
            "title": "Omega Aqua Terra 150M",
            "isDefault": true
          }
        ],
        "isActive": true
      }
    },
    {
      "id": "6a0d8905d38ea5fe36d785fa",
      "before": {
        "slug": "omega-aqua-terra-150m-y21xba",
        "images": [],
        "isActive": true
      },
      "after": {
        "slug": "omega-aqua-terra-150m-y21xba",
        "sku": "SKU-d785fa",
        "images": [],
        "variants": [
          {
            "sku": "SKU-d785fa",
            "price": 145000000,
            "title": "Omega Aqua Terra 150M",
            "isDefault": true
          }
        ],
        "isActive": true
      }
    },
    {
      "id": "6a0d8905d38ea5fe36d785fb",
      "before": {
        "slug": "omega-aqua-terra-150m-nkkt7h",
        "images": [],
        "isActive": true
      },
      "after": {
        "slug": "omega-aqua-terra-150m-nkkt7h",
        "sku": "SKU-d785fb",
        "images": [],
        "variants": [
          {
            "sku": "SKU-d785fb",
            "price": 145000000,
            "title": "Omega Aqua Terra 150M",
            "isDefault": true
          }
        ],
        "isActive": true
      }
    },
    {
      "id": "6a0d8905d38ea5fe36d785fc",
      "before": {
        "slug": "omega-aqua-terra-150m-3p1i3",
        "images": [],
        "isActive": true
      },
      "after": {
        "slug": "omega-aqua-terra-150m-3p1i3",
        "sku": "SKU-d785fc",
        "images": [],
        "variants": [
          {
            "sku": "SKU-d785fc",
            "price": 145000000,
            "title": "Omega Aqua Terra 150M",
            "isDefault": true
          }
        ],
        "isActive": true
      }
    },
    {
      "id": "6a0d8905d38ea5fe36d785fd",
      "before": {
        "slug": "omega-aqua-terra-150m-v0n7ym",
        "images": [],
        "isActive": true
      },
      "after": {
        "slug": "omega-aqua-terra-150m-v0n7ym",
        "sku": "SKU-d785fd",
        "images": [],
        "variants": [
          {
            "sku": "SKU-d785fd",
            "price": 145000000,
            "title": "Omega Aqua Terra 150M",
            "isDefault": true
          }
        ],
        "isActive": true
      }
    },
    {
      "id": "6a0d8905d38ea5fe36d785fe",
      "before": {
        "slug": "omega-aqua-terra-150m-r66qt",
        "images": [],
        "isActive": true
      },
      "after": {
        "slug": "omega-aqua-terra-150m-r66qt",
        "sku": "SKU-d785fe",
        "images": [],
        "variants": [
          {
            "sku": "SKU-d785fe",
            "price": 145000000,
            "title": "Omega Aqua Terra 150M",
            "isDefault": true
          }
        ],
        "isActive": true
      }
    },
    {
      "id": "6a0d8905d38ea5fe36d785ff",
      "before": {
        "slug": "omega-planet-ocean-600m-fna36i",
        "images": [],
        "isActive": true
      },
      "after": {
        "slug": "omega-planet-ocean-600m-fna36i",
        "sku": "SKU-d785ff",
        "images": [],
        "variants": [
          {
            "sku": "SKU-d785ff",
            "price": 160000000,
            "title": "Omega Planet Ocean 600M",
            "isDefault": true
          }
        ],
        "isActive": true
      }
    },
    {
      "id": "6a0d8905d38ea5fe36d78600",
      "before": {
        "slug": "omega-planet-ocean-600m-psadzh",
        "images": [],
        "isActive": true
      },
      "after": {
        "slug": "omega-planet-ocean-600m-psadzh",
        "sku": "SKU-d78600",
        "images": [],
        "variants": [
          {
            "sku": "SKU-d78600",
            "price": 160000000,
            "title": "Omega Planet Ocean 600M",
            "isDefault": true
          }
        ],
        "isActive": true
      }
    }
  ]
}